{
  "annotations": {
    "list": [
      {
        "builtIn": 1,
        "datasource": "-- Grafana --",
        "enable": true,
        "hide": true,
        "iconColor": "rgba(0, 211, 255, 1)",
        "limit": 100,
        "name": "Annotations & Alerts",
        "showIn": 0,
        "type": "dashboard"
      }
    ]
  },
  "description": "Generic dashboard for Quarkus apps",
  "editable": true,
  "gnetId": null,
  "graphTooltip": 1,
  "id": 3,
  "iteration": 1624445296221,
  "links": [
    {
      "icon": "external link",
      "tags": [],
      "title": "Sources",
      "type": "link",
      "url": "https://github.com/lwitkowski/quarkus-grafana-dashboard"
    }
  ],
  "panels": [
    {
      "collapsed": false,
      "datasource": null,
      "gridPos": {
        "h": 1,
        "w": 24,
        "x": 0,
        "y": 0
      },
      "id": 125,
      "panels": [],
      "repeat": null,
      "title": "Quick Facts",
      "type": "row"
    },
    {
      "cacheTimeout": null,
      "datasource": "${DS_PROMETHEUS}",
      "fieldConfig": {
        "defaults": {
          "decimals": 1,
          "mappings": [
            {
              "id": 0,
              "op": "=",
              "text": "N/A",
              "type": 1,
              "value": "null"
            }
          ],
          "thresholds": {
            "mode": "absolute",
            "steps": [
              {
                "color": "red",
                "value": null
              },
              {
                "color": "green",
                "value": 300
              }
            ]
          },
          "unit": "s"
        },
        "overrides": []
      },
      "gridPos": {
        "h": 3,
        "w": 3,
        "x": 0,
        "y": 1
      },
      "id": 63,
      "interval": null,
      "links": [],
      "maxDataPoints": 100,
      "options": {
        "colorMode": "value",
        "fieldOptions": {
          "calcs": [
            "lastNotNull"
          ]
        },
        "graphMode": "none",
        "justifyMode": "auto",
        "orientation": "horizontal",
        "reduceOptions": {
          "calcs": [
            "lastNotNull"
          ],
          "fields": "",
          "values": false
        },
        "text": {},
        "textMode": "auto"
      },
      "pluginVersion": "7.5.2",
      "targets": [
        {
          "exemplar": true,
          "expr": "sum(process_uptime_seconds{pod=\"$instance\"})",
          "format": "time_series",
          "interval": "",
          "intervalFactor": 2,
          "legendFormat": "",
          "metric": "",
          "refId": "A",
          "step": 14400
        }
      ],
      "title": "Uptime",
      "type": "stat"
    },
    {
      "datasource": "$DS_PROMETHEUS",
      "description": "",
      "fieldConfig": {
        "defaults": {
          "decimals": 2,
          "mappings": [],
          "thresholds": {
            "mode": "absolute",
            "steps": [
              {
                "color": "green",
                "value": null
              },
              {
                "color": "red",
                "value": 80
              }
            ]
          },
          "unit": "percentunit"
        },
        "overrides": []
      },
      "gridPos": {
        "h": 3,
        "w": 2,
        "x": 3,
        "y": 1
      },
      "id": 140,
      "options": {
        "orientation": "auto",
        "reduceOptions": {
          "calcs": [
            "lastNotNull"
          ],
          "fields": "",
          "values": false
        },
        "showThresholdLabels": false,
        "showThresholdMarkers": true,
        "text": {}
      },
      "pluginVersion": "7.5.2",
      "targets": [
        {
          "exemplar": true,
          "expr": "sum(system_cpu_usage{pod=\"$instance\"})",
          "format": "time_series",
          "interval": "",
          "legendFormat": " ",
          "refId": "A"
        }
      ],
      "timeFrom": null,
      "timeShift": null,
      "title": "CPU",
      "type": "gauge"
    },
    {
      "cacheTimeout": null,
      "datasource": "${DS_PROMETHEUS}",
      "description": "Used / max heap memory",
      "fieldConfig": {
        "defaults": {
          "decimals": 0,
          "mappings": [
            {
              "id": 0,
              "op": "=",
              "text": "N/A",
              "type": 1,
              "value": "null"
            }
          ],
          "thresholds": {
            "mode": "absolute",
            "steps": [
              {
                "color": "rgba(50, 172, 45, 0.97)",
                "value": null
              },
              {
                "color": "rgba(237, 129, 40, 0.89)",
                "value": 70
              },
              {
                "color": "rgba(245, 54, 54, 0.9)",
                "value": 90
              }
            ]
          },
          "unit": "percent"
        },
        "overrides": []
      },
      "gridPos": {
        "h": 3,
        "w": 2,
        "x": 5,
        "y": 1
      },
      "id": 65,
      "interval": null,
      "links": [],
      "maxDataPoints": 100,
      "options": {
        "orientation": "horizontal",
        "reduceOptions": {
          "calcs": [
            "lastNotNull"
          ],
          "fields": "",
          "values": false
        },
        "showThresholdLabels": false,
        "showThresholdMarkers": true,
        "text": {}
      },
      "pluginVersion": "7.5.2",
      "targets": [
        {
          "exemplar": true,
          "expr": "sum(jvm_memory_used_bytes{pod=\"$instance\"}*100)/sum(jvm_memory_max_bytes{pod=\"$instance\"})",
          "format": "time_series",
          "interval": "",
          "intervalFactor": 2,
          "legendFormat": " ",
          "refId": "A",
          "step": 14400
        }
      ],
      "timeFrom": null,
      "timeShift": null,
      "title": "Mem",
      "type": "gauge"
    },
    {
      "cacheTimeout": null,
      "datasource": "${DS_PROMETHEUS}",
      "description": "",
      "fieldConfig": {
        "defaults": {
          "decimals": 0,
          "mappings": [],
          "noValue": "0",
          "thresholds": {
            "mode": "absolute",
            "steps": [
              {
                "color": "rgba(50, 172, 45, 0.97)",
                "value": null
              }
            ]
          },
          "unit": "short"
        },
        "overrides": []
      },
      "gridPos": {
        "h": 3,
        "w": 7,
        "x": 7,
        "y": 1
      },
      "id": 155,
      "interval": null,
      "links": [],
      "maxDataPoints": 100,
      "options": {
        "colorMode": "value",
        "graphMode": "none",
        "justifyMode": "auto",
        "orientation": "auto",
        "reduceOptions": {
          "calcs": [
            "last"
          ],
          "fields": "",
          "values": false
        },
        "text": {},
        "textMode": "auto"
      },
      "pluginVersion": "7.5.2",
      "targets": [
        {
          "exemplar": true,
          "expr": "round(sum(increase(http_server_requests_seconds_count{namespace=\"$namespace\", service=\"$service\"}[1m])))/60",
          "format": "time_series",
          "hide": false,
          "instant": false,
          "interval": "",
          "intervalFactor": 1,
          "legendFormat": "Requests per Second",
          "refId": "per_minute",
          "step": 14400
        },
        {
          "exemplar": true,
          "expr": "round(sum(increase(http_server_requests_seconds_count{namespace=\"$namespace\", service=\"$service\"}[$__range])))",
          "hide": false,
          "interval": "",
          "legendFormat": "Total Requests",
          "refId": "total"
        }
      ],
      "timeFrom": null,
      "timeShift": null,
      "title": "Num of Requests",
      "type": "stat"
    },
    {
      "cacheTimeout": null,
      "datasource": "${DS_PROMETHEUS}",
      "description": "Failed requests in last 1 minute",
      "fieldConfig": {
        "defaults": {
          "decimals": 0,
          "mappings": [
            {
              "id": 0,
              "op": "=",
              "text": "N/A",
              "type": 1,
              "value": "null"
            }
          ],
          "thresholds": {
            "mode": "absolute",
            "steps": [
              {
                "color": "rgba(50, 172, 45, 0.97)",
                "value": null
              },
              {
                "color": "rgba(237, 129, 40, 0.89)",
                "value": 20
              },
              {
                "color": "rgba(245, 54, 54, 0.9)",
                "value": 50
              }
            ]
          },
          "unit": "percent"
        },
        "overrides": []
      },
      "gridPos": {
        "h": 3,
        "w": 2,
        "x": 14,
        "y": 1
      },
      "id": 158,
      "interval": null,
      "links": [],
      "maxDataPoints": 100,
      "options": {
        "orientation": "horizontal",
        "reduceOptions": {
          "calcs": [
            "lastNotNull"
          ],
          "fields": "",
          "values": false
        },
        "showThresholdLabels": false,
        "showThresholdMarkers": true,
        "text": {}
      },
      "pluginVersion": "7.5.2",
      "targets": [
        {
          "exemplar": true,
          "expr": "rate(locust_stats_num_failures{path=\"Aggregated\"}[1m]) * 100 /rate(locust_stats_num_requests{path=\"Aggregated\"}[1m])",
          "format": "time_series",
          "interval": "",
          "intervalFactor": 2,
          "legendFormat": " ",
          "refId": "A",
          "step": 14400
        }
      ],
      "timeFrom": null,
      "timeShift": null,
      "title": "% failed",
      "type": "gauge"
    },
    {
      "cacheTimeout": null,
      "datasource": "${DS_PROMETHEUS}",
      "description": "failure rate by Locust",
      "fieldConfig": {
        "defaults": {
          "color": {
            "mode": "thresholds"
          },
          "decimals": 0,
          "mappings": [
            {
              "id": 0,
              "op": "=",
              "text": "N/A",
              "type": 1,
              "value": "null"
            }
          ],
          "thresholds": {
            "mode": "absolute",
            "steps": [
              {
                "color": "rgba(50, 172, 45, 0.97)",
                "value": null
              },
              {
                "color": "rgba(237, 129, 40, 0.89)",
                "value": 20
              },
              {
                "color": "rgba(245, 54, 54, 0.9)",
                "value": 50
              }
            ]
          },
          "unit": "percent"
        },
        "overrides": []
      },
      "gridPos": {
        "h": 3,
        "w": 2,
        "x": 16,
        "y": 1
      },
      "id": 159,
      "interval": null,
      "links": [],
      "maxDataPoints": 100,
      "options": {
        "orientation": "horizontal",
        "reduceOptions": {
          "calcs": [
            "lastNotNull"
          ],
          "fields": "",
          "values": false
        },
        "showThresholdLabels": false,
        "showThresholdMarkers": true,
        "text": {}
      },
      "pluginVersion": "7.5.2",
      "targets": [
        {
          "exemplar": true,
          "expr": "avg_over_time(locust_fail_ratio[5m])",
          "format": "time_series",
          "interval": "",
          "intervalFactor": 2,
          "legendFormat": " ",
          "refId": "A",
          "step": 14400
        }
      ],
      "timeFrom": null,
      "timeShift": null,
      "title": "% failed",
      "type": "gauge"
    },
    {
      "collapsed": false,
      "datasource": null,
      "gridPos": {
        "h": 1,
        "w": 24,
        "x": 0,
        "y": 4
      },
      "id": 147,
      "panels": [],
      "title": "HTTP (cluster)",
      "type": "row"
    },
    {
      "aliasColors": {},
      "bars": false,
      "dashLength": 10,
      "dashes": false,
      "datasource": "$DS_PROMETHEUS",
      "description": "HTTP average response times over last [1m] for all instances in a cluster.\n\nPlease mind that response time displayed here is measured inside JVM, it is not full end to end latency your users see, which can be few times bigger.\n\nAdd this to your application.properties first:\nquarkus.resteasy.metrics.enabled=true",
      "fieldConfig": {
        "defaults": {
          "links": [],
          "unit": "s"
        },
        "overrides": []
      },
      "fill": 1,
      "fillGradient": 0,
      "gridPos": {
        "h": 8,
        "w": 12,
        "x": 6,
        "y": 5
      },
      "hiddenSeries": false,
      "id": 154,
      "legend": {
        "alignAsTable": false,
        "avg": false,
        "current": false,
        "hideEmpty": true,
        "hideZero": true,
        "max": false,
        "min": false,
        "rightSide": true,
        "show": false,
        "total": false,
        "values": false
      },
      "lines": true,
      "linewidth": 1,
      "nullPointMode": "null",
      "options": {
        "alertThreshold": true
      },
      "percentage": false,
      "pluginVersion": "7.5.2",
      "pointradius": 2,
      "points": false,
      "renderer": "flot",
      "seriesOverrides": [],
      "spaceLength": 10,
      "stack": false,
      "steppedLine": false,
      "targets": [
        {
          "exemplar": true,
          "expr": "http_server_requests_seconds_max{status=~\"2..\", uri=~\"/accounts.*\"}",
          "hide": false,
          "interval": "",
          "legendFormat": "current",
          "refId": "C"
        },
        {
          "exemplar": true,
          "expr": "avg_over_time(http_server_requests_seconds_max{status=~\"2..\", uri=~\"/accounts.*\"}[15m])",
          "hide": false,
          "interval": "",
          "legendFormat": "15 min avg",
          "refId": "A"
        }
      ],
      "thresholds": [],
      "timeFrom": null,
      "timeRegions": [],
      "timeShift": null,
      "title": "Avg server response times",
      "tooltip": {
        "shared": true,
        "sort": 0,
        "value_type": "individual"
      },
      "type": "graph",
      "xaxis": {
        "buckets": null,
        "mode": "time",
        "name": null,
        "show": true,
        "values": []
      },
      "yaxes": [
        {
          "$$hashKey": "object:3597",
          "format": "s",
          "label": "",
          "logBase": 1,
          "max": null,
          "min": null,
          "show": true
        },
        {
          "$$hashKey": "object:3598",
          "format": "s",
          "label": null,
          "logBase": 1,
          "max": null,
          "min": null,
          "show": false
        }
      ],
      "yaxis": {
        "align": false,
        "alignLevel": null
      }
    },
    {
      "collapsed": false,
      "datasource": null,
      "gridPos": {
        "h": 1,
        "w": 24,
        "x": 0,
        "y": 13
      },
      "id": 128,
      "panels": [],
      "repeat": null,
      "title": "Hardware utilisation",
      "type": "row"
    },
    {
      "aliasColors": {},
      "bars": false,
      "dashLength": 10,
      "dashes": false,
      "datasource": "${DS_PROMETHEUS}",
      "description": "",
      "editable": true,
      "error": false,
      "fieldConfig": {
        "defaults": {
          "links": []
        },
        "overrides": []
      },
      "fill": 1,
      "fillGradient": 0,
      "grid": {
        "leftLogBase": 1,
        "leftMax": null,
        "leftMin": null,
        "rightLogBase": 1,
        "rightMax": null,
        "rightMin": null
      },
      "gridPos": {
        "h": 7,
        "w": 6,
        "x": 0,
        "y": 14
      },
      "hiddenSeries": false,
      "id": 106,
      "legend": {
        "avg": false,
        "current": false,
        "max": false,
        "min": false,
        "show": false,
        "total": false,
        "values": false
      },
      "lines": true,
      "linewidth": 1,
      "links": [],
      "nullPointMode": "null",
      "options": {
        "alertThreshold": true
      },
      "percentage": false,
      "pluginVersion": "7.5.2",
      "pointradius": 5,
      "points": false,
      "renderer": "flot",
      "seriesOverrides": [],
      "spaceLength": 10,
      "stack": false,
      "steppedLine": false,
      "targets": [
        {
          "exemplar": true,
          "expr": "sum(system_cpu_usage{pod=\"$instance\"})",
          "format": "time_series",
          "hide": false,
          "interval": "",
          "intervalFactor": 1,
          "legendFormat": "Usage for the JVM process. 100% means that all CPUs were actively running threads from the JVM",
          "refId": "B"
        },
        {
          "exemplar": true,
          "expr": "sum(avg_over_time(system_cpu_usage{pod=\"$instance\"}[15m]))",
          "hide": false,
          "interval": "",
          "legendFormat": "",
          "refId": "A"
        }
      ],
      "thresholds": [],
      "timeFrom": null,
      "timeRegions": [],
      "timeShift": null,
      "title": "CPU Usage",
      "tooltip": {
        "msResolution": false,
        "shared": true,
        "sort": 0,
        "value_type": "cumulative"
      },
      "type": "graph",
      "x-axis": true,
      "xaxis": {
        "buckets": null,
        "mode": "time",
        "name": null,
        "show": true,
        "values": []
      },
      "y-axis": true,
      "y_formats": [
        "short",
        "short"
      ],
      "yaxes": [
        {
          "$$hashKey": "object:2862",
          "decimals": 1,
          "format": "percentunit",
          "label": "",
          "logBase": 1,
          "max": null,
          "min": 0,
          "show": true
        },
        {
          "$$hashKey": "object:2863",
          "format": "short",
          "label": null,
          "logBase": 1,
          "max": null,
          "min": null,
          "show": true
        }
      ],
      "yaxis": {
        "align": false,
        "alignLevel": null
      }
    },
    {
      "aliasColors": {},
      "bars": false,
      "dashLength": 10,
      "dashes": false,
      "datasource": "${DS_PROMETHEUS}",
      "description": "",
      "editable": true,
      "error": false,
      "fieldConfig": {
        "defaults": {
          "links": []
        },
        "overrides": []
      },
      "fill": 1,
      "fillGradient": 0,
      "grid": {
        "leftLogBase": 1,
        "leftMax": null,
        "leftMin": null,
        "rightLogBase": 1,
        "rightMax": null,
        "rightMin": null
      },
      "gridPos": {
        "h": 7,
        "w": 6,
        "x": 6,
        "y": 14
      },
      "hiddenSeries": false,
      "id": 93,
      "legend": {
        "avg": false,
        "current": false,
        "max": false,
        "min": false,
        "show": false,
        "total": false,
        "values": false
      },
      "lines": true,
      "linewidth": 1,
      "links": [],
      "nullPointMode": "null",
      "options": {
        "alertThreshold": true
      },
      "percentage": false,
      "pluginVersion": "7.5.2",
      "pointradius": 5,
      "points": false,
      "renderer": "flot",
      "seriesOverrides": [],
      "spaceLength": 10,
      "stack": false,
      "steppedLine": false,
      "targets": [
        {
          "exemplar": true,
          "expr": "sum(system_load_average_1m{pod=\"$instance\"})",
          "format": "time_series",
          "interval": "",
          "intervalFactor": 1,
          "legendFormat": "Load average 1 min",
          "metric": "",
          "refId": "A",
          "step": 2400
        },
        {
          "exemplar": true,
          "expr": "sum(avg_over_time(system_load_average_1m{pod=\"$instance\"}[15m]))",
          "hide": false,
          "interval": "",
          "legendFormat": "Load average 15 mins",
          "refId": "B"
        }
      ],
      "thresholds": [],
      "timeFrom": null,
      "timeRegions": [],
      "timeShift": null,
      "title": "Load",
      "tooltip": {
        "msResolution": false,
        "shared": true,
        "sort": 0,
        "value_type": "cumulative"
      },
      "type": "graph",
      "x-axis": true,
      "xaxis": {
        "buckets": null,
        "mode": "time",
        "name": null,
        "show": true,
        "values": []
      },
      "y-axis": true,
      "y_formats": [
        "short",
        "short"
      ],
      "yaxes": [
        {
          "$$hashKey": "object:3116",
          "decimals": 1,
          "format": "short",
          "label": "",
          "logBase": 1,
          "max": null,
          "min": 0,
          "show": true
        },
        {
          "$$hashKey": "object:3117",
          "format": "short",
          "label": null,
          "logBase": 1,
          "max": null,
          "min": null,
          "show": true
        }
      ],
      "yaxis": {
        "align": false,
        "alignLevel": null
      }
    },
    {
      "aliasColors": {},
      "bars": false,
      "dashLength": 10,
      "dashes": false,
      "datasource": "${DS_PROMETHEUS}",
      "editable": true,
      "error": false,
      "fieldConfig": {
        "defaults": {
          "links": []
        },
        "overrides": []
      },
      "fill": 1,
      "fillGradient": 0,
      "grid": {
        "leftLogBase": 1,
        "leftMax": null,
        "leftMin": null,
        "rightLogBase": 1,
        "rightMax": null,
        "rightMin": null
      },
      "gridPos": {
        "h": 7,
        "w": 6,
        "x": 12,
        "y": 14
      },
      "hiddenSeries": false,
      "id": 32,
      "legend": {
        "avg": false,
        "current": false,
        "max": false,
        "min": false,
        "show": false,
        "total": false,
        "values": false
      },
      "lines": true,
      "linewidth": 1,
      "links": [],
      "nullPointMode": "null",
      "options": {
        "alertThreshold": true
      },
      "percentage": false,
      "pluginVersion": "7.5.2",
      "pointradius": 5,
      "points": false,
      "renderer": "flot",
      "seriesOverrides": [],
      "spaceLength": 10,
      "stack": false,
      "steppedLine": false,
      "targets": [
        {
          "exemplar": true,
          "expr": "jvm_threads_live_threads",
          "format": "time_series",
          "interval": "",
          "intervalFactor": 2,
          "legendFormat": "Live threads $instance",
          "metric": "",
          "refId": "A",
          "step": 2400
        },
        {
          "exemplar": true,
          "expr": "jvm_threads_peak_threads",
          "format": "time_series",
          "hide": false,
          "interval": "",
          "intervalFactor": 2,
          "legendFormat": "Peak threads $instance",
          "refId": "D",
          "step": 2400
        }
      ],
      "thresholds": [],
      "timeFrom": null,
      "timeRegions": [],
      "timeShift": null,
      "title": "Threads",
      "tooltip": {
        "msResolution": false,
        "shared": true,
        "sort": 0,
        "value_type": "cumulative"
      },
      "type": "graph",
      "x-axis": true,
      "xaxis": {
        "buckets": null,
        "mode": "time",
        "name": null,
        "show": true,
        "values": []
      },
      "y-axis": true,
      "y_formats": [
        "short",
        "short"
      ],
      "yaxes": [
        {
          "$$hashKey": "object:2948",
          "decimals": 0,
          "format": "short",
          "label": null,
          "logBase": 1,
          "max": null,
          "min": 0,
          "show": true
        },
        {
          "$$hashKey": "object:2949",
          "format": "short",
          "label": null,
          "logBase": 1,
          "max": null,
          "min": null,
          "show": true
        }
      ],
      "yaxis": {
        "align": false,
        "alignLevel": null
      }
    },
    {
      "collapsed": false,
      "datasource": null,
      "gridPos": {
        "h": 1,
        "w": 24,
        "x": 0,
        "y": 21
      },
      "id": 134,
      "panels": [],
      "repeat": null,
      "title": "Datasource (Agroal)",
      "type": "row"
    },
    {
      "aliasColors": {},
      "bars": false,
      "dashLength": 10,
      "dashes": false,
      "datasource": "$DS_PROMETHEUS",
      "description": "",
      "fieldConfig": {
        "defaults": {
          "links": []
        },
        "overrides": []
      },
      "fill": 1,
      "fillGradient": 0,
      "gridPos": {
        "h": 8,
        "w": 12,
        "x": 0,
        "y": 22
      },
      "hiddenSeries": false,
      "id": 138,
      "legend": {
        "avg": false,
        "current": false,
        "max": false,
        "min": false,
        "show": false,
        "total": false,
        "values": false
      },
      "lines": true,
      "linewidth": 1,
      "nullPointMode": "null",
      "options": {
        "alertThreshold": false
      },
      "percentage": false,
      "pluginVersion": "7.5.2",
      "pointradius": 2,
      "points": false,
      "renderer": "flot",
      "seriesOverrides": [],
      "spaceLength": 10,
      "stack": false,
      "steppedLine": false,
      "targets": [
        {
          "exemplar": true,
          "expr": "agroal_active_count{service=\"accounts\"}",
          "hide": false,
          "interval": "",
          "legendFormat": "Active $instance",
          "refId": "H"
        },
        {
          "exemplar": true,
          "expr": "agroal_awaiting_count{service=\"accounts\"}",
          "interval": "",
          "legendFormat": "Awaiting $instance",
          "refId": "D"
        }
      ],
      "thresholds": [],
      "timeFrom": null,
      "timeRegions": [],
      "timeShift": null,
      "title": "JDBC connection pool active / awaiting",
      "tooltip": {
        "shared": true,
        "sort": 0,
        "value_type": "individual"
      },
      "type": "graph",
      "xaxis": {
        "buckets": null,
        "mode": "time",
        "name": null,
        "show": true,
        "values": []
      },
      "yaxes": [
        {
          "$$hashKey": "object:1049",
          "decimals": null,
          "format": "short",
          "label": "Connections",
          "logBase": 1,
          "max": null,
          "min": "0",
          "show": true
        },
        {
          "$$hashKey": "object:1050",
          "format": "short",
          "label": null,
          "logBase": 1,
          "max": null,
          "min": null,
          "show": true
        }
      ],
      "yaxis": {
        "align": false,
        "alignLevel": null
      }
    },
    {
      "aliasColors": {},
      "bars": false,
      "dashLength": 10,
      "dashes": false,
      "datasource": "$DS_PROMETHEUS",
      "description": "",
      "fieldConfig": {
        "defaults": {
          "links": []
        },
        "overrides": []
      },
      "fill": 1,
      "fillGradient": 0,
      "gridPos": {
        "h": 8,
        "w": 12,
        "x": 12,
        "y": 22
      },
      "hiddenSeries": false,
      "id": 144,
      "legend": {
        "avg": false,
        "current": false,
        "max": false,
        "min": false,
        "show": false,
        "total": false,
        "values": false
      },
      "lines": true,
      "linewidth": 1,
      "nullPointMode": "null",
      "options": {
        "alertThreshold": true
      },
      "percentage": false,
      "pluginVersion": "7.5.2",
      "pointradius": 2,
      "points": false,
      "renderer": "flot",
      "seriesOverrides": [],
      "spaceLength": 10,
      "stack": false,
      "steppedLine": false,
      "targets": [
        {
          "exemplar": true,
          "expr": "app_db_query_duration_seconds_bucket",
          "hide": false,
          "interval": "",
          "legendFormat": "Time to acquire a connection",
          "refId": "B"
        }
      ],
      "thresholds": [],
      "timeFrom": null,
      "timeRegions": [],
      "timeShift": null,
      "title": "Timing for database quries",
      "tooltip": {
        "shared": true,
        "sort": 0,
        "value_type": "individual"
      },
      "type": "graph",
      "xaxis": {
        "buckets": null,
        "mode": "time",
        "name": null,
        "show": true,
        "values": []
      },
      "yaxes": [
        {
          "$$hashKey": "object:3367",
          "format": "s",
          "label": null,
          "logBase": 2,
          "max": null,
          "min": null,
          "show": true
        },
        {
          "$$hashKey": "object:3368",
          "format": "short",
          "label": null,
          "logBase": 1,
          "max": null,
          "min": null,
          "show": true
        }
      ],
      "yaxis": {
        "align": false,
        "alignLevel": null
      }
    },
    {
      "collapsed": false,
      "datasource": null,
      "gridPos": {
        "h": 1,
        "w": 24,
        "x": 0,
        "y": 30
      },
      "id": 131,
      "panels": [],
      "repeat": null,
      "title": "Garbage Collector",
      "type": "row"
    },
    {
      "aliasColors": {},
      "bars": false,
      "dashLength": 10,
      "dashes": false,
      "datasource": "${DS_PROMETHEUS}",
      "fieldConfig": {
        "defaults": {
          "links": []
        },
        "overrides": []
      },
      "fill": 1,
      "fillGradient": 0,
      "gridPos": {
        "h": 7,
        "w": 8,
        "x": 8,
        "y": 31
      },
      "hiddenSeries": false,
      "id": 101,
      "legend": {
        "alignAsTable": false,
        "avg": false,
        "current": false,
        "max": false,
        "min": false,
        "show": false,
        "total": false,
        "values": false
      },
      "lines": true,
      "linewidth": 1,
      "links": [],
      "nullPointMode": "null",
      "options": {
        "alertThreshold": true
      },
      "percentage": false,
      "pluginVersion": "7.5.2",
      "pointradius": 5,
      "points": false,
      "renderer": "flot",
      "seriesOverrides": [],
      "spaceLength": 10,
      "stack": false,
      "steppedLine": false,
      "targets": [
        {
          "exemplar": true,
          "expr": "sum by (name) (increase(jvm_gc_pause_seconds_count{pod=\"$instance\"}[1m]))",
          "format": "time_series",
          "hide": false,
          "instant": false,
          "interval": "",
          "intervalFactor": 1,
          "legendFormat": "Approximate accumulated collection elapsed time ({{name}})",
          "refId": "A"
        }
      ],
      "thresholds": [],
      "timeFrom": null,
      "timeRegions": [],
      "timeShift": null,
      "title": "Durations over last [1m]",
      "tooltip": {
        "shared": true,
        "sort": 0,
        "value_type": "individual"
      },
      "type": "graph",
      "xaxis": {
        "buckets": null,
        "mode": "time",
        "name": null,
        "show": true,
        "values": []
      },
      "yaxes": [
        {
          "format": "s",
          "label": null,
          "logBase": 1,
          "max": null,
          "min": "0",
          "show": true
        },
        {
          "format": "short",
          "label": "",
          "logBase": 1,
          "max": null,
          "min": null,
          "show": true
        }
      ],
      "yaxis": {
        "align": false,
        "alignLevel": null
      }
    },
    {
      "collapsed": false,
      "datasource": null,
      "gridPos": {
        "h": 1,
        "w": 24,
        "x": 0,
        "y": 38
      },
      "id": 157,
      "panels": [],
      "title": "Logs",
      "type": "row"
    }
  ],
  "refresh": "10s",
  "schemaVersion": 27,
  "style": "dark",
  "tags": [
    "quarkus",
    "java"
  ],
  "templating": {
    "list": [
      {
        "current": {
          "selected": false,
          "text": "Prometheus",
          "value": "Prometheus"
        },
        "description": null,
        "error": null,
        "hide": 0,
        "includeAll": false,
        "label": "Datasource",
        "multi": false,
        "name": "DS_PROMETHEUS",
        "options": [],
        "query": "prometheus",
        "queryValue": "",
        "refresh": 1,
        "regex": "",
        "skipUrlSync": false,
        "type": "datasource"
      },
      {
        "description": null,
        "error": null,
        "hide": 2,
        "label": "Namespace",
        "name": "namespace",
        "query": "default",
        "skipUrlSync": false,
        "type": "constant"
      },
      {
        "allValue": null,
        "current": {
          "selected": false,
          "text": "accounts",
          "value": "accounts"
        },
        "datasource": "$DS_PROMETHEUS",
        "definition": "label_values(process_uptime_seconds{namespace=\"$namespace\"}, service)",
        "description": null,
        "error": null,
        "hide": 0,
        "includeAll": false,
        "label": "Service",
        "multi": false,
        "name": "service",
        "options": [],
        "query": {
          "query": "label_values(process_uptime_seconds{namespace=\"$namespace\"}, service)",
          "refId": "StandardVariableQuery"
        },
        "refresh": 2,
        "regex": "",
        "skipUrlSync": false,
        "sort": 1,
        "tagValuesQuery": "",
        "tags": [],
        "tagsQuery": "",
        "type": "query",
        "useTags": false
      },
      {
        "allFormat": "glob",
        "allValue": null,
        "current": {
          "selected": false,
          "text": "accounts-5dbd794d7d-j746r",
          "value": "accounts-5dbd794d7d-j746r"
        },
        "datasource": "$DS_PROMETHEUS",
        "definition": "label_values(process_uptime_seconds{namespace=\"$namespace\", service=\"$service\"}, pod)",
        "description": null,
        "error": null,
        "hide": 0,
        "includeAll": false,
        "label": "Instance",
        "multi": false,
        "multiFormat": "glob",
        "name": "instance",
        "options": [],
        "query": {
          "query": "label_values(process_uptime_seconds{namespace=\"$namespace\", service=\"$service\"}, pod)",
          "refId": "StandardVariableQuery"
        },
        "refresh": 2,
        "regex": "",
        "skipUrlSync": false,
        "sort": 0,
        "tagValuesQuery": "",
        "tags": [],
        "tagsQuery": "",
        "type": "query",
        "useTags": false
      }
    ]
  },
  "time": {
    "from": "now-1h",
    "to": "now"
  },
  "timepicker": {
    "now": true,
    "refresh_intervals": [
      "10s",
      "30s",
      "1m"
    ],
    "time_options": [
      "5m",
      "15m",
      "1h",
      "6h",
      "12h",
      "24h",
      "2d",
      "7d",
      "30d"
    ]
  },
  "timezone": "browser",
  "title": "Reactive Account OpenAPI Benchmarks",
  "uid": "VRxT0ojZz",
  "version": 15
}